d1y/__init__.py
donelib-0.0.1.dist-info/METADATA
donelib-0.0.1.dist-info/WHEEL
donelib-0.0.1.dist-info/top_level.txt
donelib-0.0.1.dist-info/RECORD
